reportlabtyphon/__init__.py
reportlabtyphon/rl_config.py
reportlabtyphon/rl_settings.py
reportlabtyphon/graphics/__init__.py
reportlabtyphon/graphics/renderPDF.py
reportlabtyphon/graphics/renderPM.py
reportlabtyphon/graphics/renderPS.py
reportlabtyphon/graphics/renderSVG.py
reportlabtyphon/graphics/renderbase.py
reportlabtyphon/graphics/shapes.py
reportlabtyphon/graphics/testdrawings.py
reportlabtyphon/graphics/testshapes.py
reportlabtyphon/graphics/widgetbase.py
reportlabtyphon/graphics/barcode/__init__.py
reportlabtyphon/graphics/barcode/code128.py
reportlabtyphon/graphics/barcode/code39.py
reportlabtyphon/graphics/barcode/code93.py
reportlabtyphon/graphics/barcode/common.py
reportlabtyphon/graphics/barcode/eanbc.py
reportlabtyphon/graphics/barcode/ecc200datamatrix.py
reportlabtyphon/graphics/barcode/fourstate.py
reportlabtyphon/graphics/barcode/lto.py
reportlabtyphon/graphics/barcode/qr.py
reportlabtyphon/graphics/barcode/qrencoder.py
reportlabtyphon/graphics/barcode/test.py
reportlabtyphon/graphics/barcode/usps.py
reportlabtyphon/graphics/barcode/usps4s.py
reportlabtyphon/graphics/barcode/widgets.py
reportlabtyphon/graphics/charts/__init__.py
reportlabtyphon/graphics/charts/areas.py
reportlabtyphon/graphics/charts/axes.py
reportlabtyphon/graphics/charts/barcharts.py
reportlabtyphon/graphics/charts/dotbox.py
reportlabtyphon/graphics/charts/doughnut.py
reportlabtyphon/graphics/charts/legends.py
reportlabtyphon/graphics/charts/linecharts.py
reportlabtyphon/graphics/charts/lineplots.py
reportlabtyphon/graphics/charts/markers.py
reportlabtyphon/graphics/charts/piecharts.py
reportlabtyphon/graphics/charts/slidebox.py
reportlabtyphon/graphics/charts/spider.py
reportlabtyphon/graphics/charts/textlabels.py
reportlabtyphon/graphics/charts/utils.py
reportlabtyphon/graphics/charts/utils3d.py
reportlabtyphon/graphics/samples/__init__.py
reportlabtyphon/graphics/samples/bubble.py
reportlabtyphon/graphics/samples/clustered_bar.py
reportlabtyphon-1.0.2.dist-info/METADATA
reportlabtyphon-1.0.2.dist-info/WHEEL
reportlabtyphon-1.0.2.dist-info/top_level.txt
reportlabtyphon-1.0.2.dist-info/RECORD
