Metadata-Version: 2.1
Name: reportlabtyphon
Version: 1.0.2
Summary: reportlab Custom modification
Home-page: https://www.python.org/
Author: rrd
Author-email: rrd@rrd.com
License: MIT
Project-URL: Documentation, https://packaging.python.org/tutorials/distributing-packages/
Project-URL: Funding, https://donate.pypi.org
Project-URL: Source, https://github.com/pypa/sampleproject/
Project-URL: Tracker, https://github.com/pypa/sampleproject/issues
Keywords: ga nn
Platform: UNKNOWN
Requires-Python: >=3
